disent/__init__.py
disent/batch.py
disent/disent.py
disent/env.py
disent/environments.py
disent/settings.py
disent/spinner.py
disentpy-0.0.24.dist-info/LICENSE.md
disentpy-0.0.24.dist-info/METADATA
disentpy-0.0.24.dist-info/WHEEL
disentpy-0.0.24.dist-info/top_level.txt
disentpy-0.0.24.dist-info/RECORD
