Metadata-Version: 2.1
Name: disentpy
Version: 0.0.24
Summary: Disent API caller
Home-page: https://github.com/disentcorp/disentpy
Author: Niels lauritzen
Author-email: niels.lauritzen@disent.com
License-File: LICENSE.md
Requires-Dist: requests
Requires-Dist: pandas
Requires-Dist: numpy
